[{"name":"James","surname":"Doe","email":"jamesDoe@gmail.com","dob":"01/01/1987","avatar":"http://localhost:3000/img/authors/macbook-pro-13-og-202011.jpg","id":"qmgorbq8l306dy3h","createdAt":"2022-05-10T13:15:21.436Z","updatedAt":"2022-05-12T17:21:28.985Z"},{"name":"Harry ","surname":"Potter","email":"harrypotter@gmail.com","dob":"01/01/1787","avatar":"http://localhost:3000/img/authors/4388256_stock-vector-vector-completed-stamp.jpg","id":"qmgorbq8l306fm3v","createdAt":"2022-05-10T13:16:39.211Z","updatedAt":"2022-05-12T17:31:08.396Z"},{"name":"Francine ","surname":"Rivers","email":"framcinerivers@gmail.com","dob":"01/01/1889","avatar":"https://www.authorsguild.org/wp-content/uploads/2017/09/doug-preston-summer-bulletin-2017-authors-guild.jpg","id":"qmgore2gl307q6va","createdAt":"2022-05-10T13:52:52.293Z"},{"name":"Sarah ","surname":"Dennis","email":"sarahrike3768@gmail.com","dob":"01/01/1889","avatar":"https://www.authorsguild.org/wp-content/uploads/2017/09/doug-preston-summer-bulletin-2017-authors-guild.jpg","id":"qmgor5skl3d0zonm","createdAt":"2022-05-19T13:05:18.225Z"},{"name":"Sarah ","surname":"Dennis","email":"sarahrike3768@gmail.com","dob":"01/01/1889","avatar":"https://www.authorsguild.org/wp-content/uploads/2017/09/doug-preston-summer-bulletin-2017-authors-guild.jpg","id":"qmgor5skl3d11vcz","createdAt":"2022-05-19T13:07:00.227Z"},{"name":"Dennis ","surname":"Agelebe","email":"dennisagels@gmail.com","dob":"01/01/1890","avatar":"https://www.authorsguild.org/wp-content/uploads/2017/09/doug-preston-summer-bulletin-2017-authors-guild.jpg","id":"qmgor8kgl3d1meoy","createdAt":"2022-05-19T13:22:58.401Z"},{"name":"Dennis ","surname":"Agelebe","email":"sarahrike3768@gmail.com","dob":"01/01/1890","avatar":"https://www.authorsguild.org/wp-content/uploads/2017/09/doug-preston-summer-bulletin-2017-authors-guild.jpg","id":"qmgorag4l3d5sz9h","createdAt":"2022-05-19T15:20:03.460Z"}]
